bpw_pde/__init__.py
bpw_pde/common.py
bpw_pde/dataframe.py
bpw_pde/index.py
bpw_pde/series.py
bpw_pde-0.0a3.dist-info/LICENSE.txt
bpw_pde-0.0a3.dist-info/METADATA
bpw_pde-0.0a3.dist-info/WHEEL
bpw_pde-0.0a3.dist-info/top_level.txt
bpw_pde-0.0a3.dist-info/RECORD
